[
  {
    "id": "0",
    "title": "Pull Day",
    "videoLink": "https://www.youtube.com/watch?v=IOl42YpK_Es",
    "exercises": [
      {
        "id": "0",
        "name": "Deadlift",
        "sets": "4",
        "reps": "6",
        "weight": "60",
        "unit": "kg",
        "completed": false,
        "firstExercise": true
      },
      {
        "id": "1",
        "name": "Barbell Row",
        "sets": "3",
        "reps": "10",
        "weight": "20",
        "unit": "kg",
        "completed": false
      },
      {
        "id": "2",
        "name": "Dumbbell Pullover",
        "sets": "3",
        "reps": "12",
        "weight": "25",
        "unit": "kg",
        "completed": false
      },
      {
        "id": "3",
        "name": "Dumbbell Upright Row",
        "sets": "3",
        "reps": "12",
        "weight": "17.5",
        "unit": "kg",
        "completed": false
      },
      {
        "id": "4",
        "name": "Chin up",
        "sets": "3",
        "editableReps": "5",
        "superSet": true
      },
      {
        "id": "5",
        "name": "Tricep Overhead",
        "sets": "3",
        "reps": "12",
        "weight": "90",
        "unit": "lbs",
        "completed": false,
        "superSet": true
      }
    ]
  },
  {
    "id": "1",
    "title": "Push Day",
    "videoLink": "https://www.youtube.com/watch?v=HE45jVN7XKM",
    "exercises": [
      {
        "id": "0",
        "name": "Barbell Bench Press",
        "sets": "4",
        "reps": "6",
        "weight": "42.5",
        "unit": "kg",
        "completed": false,
        "firstExercise": true
      },
      {
        "id": "1",
        "name": "Cable Crossover",
        "sets": "4",
        "reps": "12",
        "weight": "70",
        "unit": "lbs",
        "completed": false
      },
      {
        "id": "2",
        "name": "Dumbbell Shoulder",
        "sets": "4",
        "reps": "10",
        "weight": "10",
        "unit": "kg",
        "completed": false
      },
      {
        "id": "3",
        "name": "Lateral Rise",
        "sets": "4",
        "reps": "15",
        "weight": "3",
        "unit": "kg",
        "completed": false
      },
      {
        "id": "4",
        "name": "Dumbbell Skullcrusher",
        "sets": "3",
        "reps": "12",
        "weight": "12.5",
        "unit": "kg",
        "completed": false,
        "superSet": true
      },
      {
        "id": "5",
        "name": "Waiter Curls",
        "sets": "3",
        "reps": "12",
        "weight": "17.5",
        "unit": "kg",
        "completed": false,
        "superSet": true
      }
    ]
  },
  {
    "id": "2",
    "title": "Legs Day",
    "videoLink": "https://www.youtube.com/watch?v=X6H4l9R3DnY",
    "exercises": [
      {
        "id": "0",
        "name": "Back Squat",
        "sets": "4",
        "reps": "6",
        "weight": "37.5",
        "unit": "kg",
        "completed": false,
        "firstExercise": true
      },
      {
        "id": "1",
        "name": "Hip Thrust",
        "sets": "3",
        "reps": "10",
        "weight": "25",
        "unit": "kg",
        "completed": false
      },
      {
        "id": "2",
        "name": "Reverse Lunge",
        "sets": "3",
        "reps": "12",
        "weight": "10",
        "unit": "kg",
        "completed": false
      },
      {
        "id": "3",
        "name": "Leg Curl",
        "sets": "3",
        "reps": "12",
        "weight": "40",
        "unit": "kg",
        "completed": false
      },
      {
        "id": "4",
        "name": "Calf Rise",
        "sets": "3",
        "reps": "20",
        "weight": "75",
        "unit": "kg",
        "completed": false
      }
    ]
  },
  {
    "id": "3",
    "title": "Pull Day",
    "videoLink": "https://www.youtube.com/watch?v=IOl42YpK_Es",
    "exercises": [
      {
        "id": "0",
        "name": "Sumo Deadlift",
        "sets": "3",
        "reps": "5",
        "weight": "60",
        "unit": "kg",
        "completed": false,
        "firstExercise": true
      },
      {
        "id": "1",
        "name": "Pullups",
        "sets": "3",
        "editableReps": "5"
      },
      {
        "id": "2",
        "name": "Gorilla Rows",
        "sets": "3",
        "reps": "12",
        "weight": "27.5",
        "unit": "kg",
        "completed": false
      },
      {
        "id": "3",
        "name": "Straight Arm Pushdowns",
        "sets": "3",
        "reps": "15",
        "weight": "90",
        "unit": "lbs",
        "completed": false
      },
      {
        "id": "4",
        "name": "Barbell / EZ Curls",
        "sets": "3",
        "reps": "8",
        "weight": "12.5",
        "unit": "kg",
        "completed": false,
        "superSet": true
      },
      {
        "id": "5",
        "name": "Triceps Pushdowns",
        "sets": "3",
        "reps": "12",
        "weight": "90",
        "unit": "lbs",
        "completed": false,
        "superSet": true
      }
    ]
  },
  {
    "id": "4",
    "title": "Push Day",
    "videoLink": "https://www.youtube.com/watch?v=HE45jVN7XKM",
    "exercises": [
      {
        "id": "0",
        "name": "Barbell OHP",
        "sets": "4",
        "reps": "6",
        "weight": "0",
        "unit": "kg",
        "completed": false,
        "firstExercise": true
      },
      {
        "id": "1",
        "name": "Underhand Bench Press",
        "sets": "3",
        "reps": "10",
        "weight": "0",
        "unit": "kg",
        "completed": false
      },
      {
        "id": "2",
        "name": "Abduction Rows",
        "sets": "3",
        "reps": "10",
        "weight": "0",
        "unit": "kg",
        "completed": false
      },
      {
        "id": "3",
        "name": "Floor Flys",
        "sets": "3",
        "reps": "12",
        "weight": "0",
        "unit": "kg",
        "completed": false
      },
      {
        "id": "4",
        "name": "Close Grip Bench Press",
        "sets": "3",
        "reps": "8",
        "weight": "0",
        "unit": "kg",
        "completed": false,
        "superSet": true
      },
      {
        "id": "5",
        "name": "Curl",
        "sets": "3",
        "reps": "12",
        "weight": "0",
        "unit": "kg",
        "completed": false,
        "superSet": true
      }
    ]
  }
]